amlcompass_api/__init__.py
amlcompass_api/auth.py
amlcompass_api/client.py
amlcompass_api/credentials.py
amlcompass_api/exceptions.py
amlcompass_api/response.py
amlcompass_api/services/__init__.py
amlcompass_api/services/transactions.py
amlcompass_api-0.1.3.dist-info/METADATA
amlcompass_api-0.1.3.dist-info/WHEEL
amlcompass_api-0.1.3.dist-info/licenses/LICENSE.txt
amlcompass_api-0.1.3.dist-info/RECORD
