Metadata-Version: 2.4
Name: amlcompass-api
Version: 0.1.3
Summary: A Python client library for interacting with the AML Optima Compass API.
Project-URL: Homepage, https://github.com/yarel2l/amlcompass-api
Author-email: Yarel Leyva <yarelleyva2@gmail.com>
License: MIT License
License-File: LICENSE.txt
Keywords: aml,api,compass,optima
Classifier: Development Status :: 5 - Production/Stable
Classifier: Intended Audience :: Developers
Classifier: License :: OSI Approved :: MIT License
Classifier: Operating System :: OS Independent
Classifier: Programming Language :: Python
Classifier: Programming Language :: Python :: 3
Classifier: Programming Language :: Python :: 3.8
Classifier: Programming Language :: Python :: 3.9
Classifier: Programming Language :: Python :: 3.10
Classifier: Programming Language :: Python :: 3.11
Classifier: Programming Language :: Python :: 3.12
Classifier: Topic :: Software Development :: Libraries :: Python Modules
Requires-Python: >=3.8
Requires-Dist: python-dotenv
Requires-Dist: requests
Requires-Dist: requests-oauthlib
Provides-Extra: test
Requires-Dist: pytest; extra == 'test'
